{"area":"HIMACHAL_PRADESH","area_code":"2","age":"8","total_persons":"117124","total_males":"61593","total_females":"55531","rural_persons":"106293","rural_males":"55716","rural_females":"50577","urban_persons":"10831","urban_males":"5877","urban_females":"4954"}
{"area":"HIMACHAL_PRADESH","area_code":"2","age":"9","total_persons":"119100","total_males":"63574","total_females":"55526","rural_persons":"108190","rural_males":"57600","rural_females":"50590","urban_persons":"10910","urban_males":"5974","urban_females":"4936"}
{"area":"HIMACHAL_PRADESH","area_code":"2","age":"10","total_persons":"134596","total_males":"71647","total_females":"62949","rural_persons":"122334","rural_males":"64852","rural_females":"57482","urban_persons":"12262","urban_males":"6795","urban_females":"5467"}
{"area":"HIMACHAL_PRADESH","area_code":"2","age":"11","total_persons":"127447","total_males":"67693","total_females":"59754","rural_persons":"115507","rural_males":"61000","rural_females":"54507","urban_persons":"11940","urban_males":"6693","urban_females":"5247"}
{"area":"HIMACHAL_PRADESH","area_code":"2","age":"12","total_persons":"125830","total_males":"66799","total_females":"59031","rural_persons":"114237","rural_males":"60324","rural_females":"53913","urban_persons":"11593","urban_males":"6475","urban_females":"5118"}
{"area":"HIMACHAL_PRADESH","area_code":"2","age":"13","total_persons":"124125","total_males":"65336","total_females":"58789","rural_persons":"112678","rural_males":"59005","rural_females":"53673","urban_persons":"11447","urban_males":"6331","urban_females":"5116"}
{"area":"HIMACHAL_PRADESH","area_code":"2","age":"14","total_persons":"127226","total_males":"66765","total_females":"60461","rural_persons":"115509","rural_males":"60319","rural_females":"55190","urban_persons":"11717","urban_males":"6446","urban_females":"5271"}
{"area":"HIMACHAL_PRADESH","area_code":"2","age":"15","total_persons":"127378","total_males":"67225","total_females":"60153","rural_persons":"115114","rural_males":"60443","rural_females":"54671","urban_persons":"12264","urban_males":"6782","urban_females":"5482"}
{"area":"HIMACHAL_PRADESH","area_code":"2","age":"16","total_persons":"126410","total_males":"66658","total_females":"59752","rural_persons":"114081","rural_males":"59746","rural_females":"54335","urban_persons":"12329","urban_males":"6912","urban_females":"5417"}
{"area":"HIMACHAL_PRADESH","area_code":"2","age":"17","total_persons":"124585","total_males":"65721","total_females":"58864","rural_persons":"112339","rural_males":"59015","rural_females":"53324","urban_persons":"12246","urban_males":"6706","urban_females":"5540"}
{"area":"HIMACHAL_PRADESH","area_code":"2","age":"18","total_persons":"136759","total_males":"72265","total_females":"64494","rural_persons":"122520","rural_males":"64005","rural_females":"58515","urban_persons":"14239","urban_males":"8260","urban_females":"5979"}
{"area":"HIMACHAL_PRADESH","area_code":"2","age":"19","total_persons":"125329","total_males":"64860","total_females":"60469","rural_persons":"111937","rural_males":"57345","rural_females":"54592","urban_persons":"13392","urban_males":"7515","urban_females":"5877"}
{"area":"HIMACHAL_PRADESH","area_code":"2","age":"20","total_persons":"135902","total_males":"69643","total_females":"66259","rural_persons":"121043","rural_males":"61334","rural_females":"59709","urban_persons":"14859","urban_males":"8309","urban_females":"6550"}
{"area":"HIMACHAL_PRADESH","area_code":"2","age":"21","total_persons":"126638","total_males":"63969","total_females":"62669","rural_persons":"112829","rural_males":"56431","rural_females":"56398","urban_persons":"13809","urban_males":"7538","urban_females":"6271"}
{"area":"HIMACHAL_PRADESH","area_code":"2","age":"22","total_persons":"133018","total_males":"66720","total_females":"66298","rural_persons":"118602","rural_males":"58777","rural_females":"59825","urban_persons":"14416","urban_males":"7943","urban_females":"6473"}
{"area":"HIMACHAL_PRADESH","area_code":"2","age":"23","total_persons":"123650","total_males":"61664","total_females":"61986","rural_persons":"109984","rural_males":"54260","rural_females":"55724","urban_persons":"13666","urban_males":"7404","urban_females":"6262"}
{"area":"HIMACHAL_PRADESH","area_code":"2","age":"24","total_persons":"124658","total_males":"61724","total_females":"62934","rural_persons":"110981","rural_males":"54365","rural_females":"56616","urban_persons":"13677","urban_males":"7359","urban_females":"6318"}
{"area":"HIMACHAL_PRADESH","area_code":"2","age":"25","total_persons":"128871","total_males":"63006","total_females":"65865","rural_persons":"114397","rural_males":"55148","rural_females":"59249","urban_persons":"14474","urban_males":"7858","urban_females":"6616"}
{"area":"HIMACHAL_PRADESH","area_code":"2","age":"26","total_persons":"121425","total_males":"59721","total_females":"61704","rural_persons":"107865","rural_males":"52387","rural_females":"55478","urban_persons":"13560","urban_males":"7334","urban_females":"6226"}
{"area":"HIMACHAL_PRADESH","area_code":"2","age":"27","total_persons":"114008","total_males":"56142","total_females":"57866","rural_persons":"101455","rural_males":"49364","rural_females":"52091","urban_persons":"12553","urban_males":"6778","urban_females":"5775"}
{"area":"HIMACHAL_PRADESH","area_code":"2","age":"28","total_persons":"123493","total_males":"60448","total_females":"63045","rural_persons":"110002","rural_males":"53391","rural_females":"56611","urban_persons":"13491","urban_males":"7057","urban_females":"6434"}
{"area":"HIMACHAL_PRADESH","area_code":"2","age":"29","total_persons":"101363","total_males":"50808","total_females":"50555","rural_persons":"89886","rural_males":"44726","rural_females":"45160","urban_persons":"11477","urban_males":"6082","urban_females":"5395"}
{"area":"HIMACHAL_PRADESH","area_code":"2","age":"30","total_persons":"135071","total_males":"65731","total_females":"69340","rural_persons":"120600","rural_males":"57989","rural_females":"62611","urban_persons":"14471","urban_males":"7742","urban_females":"6729"}
{"area":"HIMACHAL_PRADESH","area_code":"2","age":"31","total_persons":"104067","total_males":"52399","total_females":"51668","rural_persons":"92304","rural_males":"46129","rural_females":"46175","urban_persons":"11763","urban_males":"6270","urban_females":"5493"}
{"area":"HIMACHAL_PRADESH","area_code":"2","age":"32","total_persons":"110340","total_males":"54497","total_females":"55843","rural_persons":"97821","rural_males":"48061","rural_females":"49760","urban_persons":"12519","urban_males":"6436","urban_females":"6083"}
{"area":"HIMACHAL_PRADESH","area_code":"2","age":"33","total_persons":"93801","total_males":"47270","total_females":"46531","rural_persons":"83163","rural_males":"41684","rural_females":"41479","urban_persons":"10638","urban_males":"5586","urban_females":"5052"}
{"area":"HIMACHAL_PRADESH","area_code":"2","age":"34","total_persons":"103078","total_males":"51356","total_females":"51722","rural_persons":"91487","rural_males":"45409","rural_females":"46078","urban_persons":"11591","urban_males":"5947","urban_females":"5644"}
{"area":"HIMACHAL_PRADESH","area_code":"2","age":"35","total_persons":"128559","total_males":"63321","total_females":"65238","rural_persons":"114437","rural_males":"55824","rural_females":"58613","urban_persons":"14122","urban_males":"7497","urban_females":"6625"}
{"area":"HIMACHAL_PRADESH","area_code":"2","age":"36","total_persons":"107410","total_males":"53799","total_females":"53611","rural_persons":"95265","rural_males":"47474","rural_females":"47791","urban_persons":"12145","urban_males":"6325","urban_females":"5820"}
{"area":"HIMACHAL_PRADESH","area_code":"2","age":"37","total_persons":"91723","total_males":"46457","total_females":"45266","rural_persons":"80940","rural_males":"40961","rural_females":"39979","urban_persons":"10783","urban_males":"5496","urban_females":"5287"}
{"area":"HIMACHAL_PRADESH","area_code":"2","age":"38","total_persons":"108396","total_males":"52845","total_females":"55551","rural_persons":"96474","rural_males":"46860","rural_females":"49614","urban_persons":"11922","urban_males":"5985","urban_females":"5937"}
{"area":"HIMACHAL_PRADESH","area_code":"2","age":"39","total_persons":"81878","total_males":"41808","total_females":"40070","rural_persons":"72159","rural_males":"36787","rural_females":"35372","urban_persons":"9719","urban_males":"5021","urban_females":"4698"}
{"area":"HIMACHAL_PRADESH","area_code":"2","age":"40","total_persons":"126089","total_males":"60353","total_females":"65736","rural_persons":"113152","rural_males":"53625","rural_females":"59527","urban_persons":"12937","urban_males":"6728","urban_females":"6209"}
{"area":"HIMACHAL_PRADESH","area_code":"2","age":"41","total_persons":"83062","total_males":"42875","total_females":"40187","rural_persons":"72936","rural_males":"37447","rural_females":"35489","urban_persons":"10126","urban_males":"5428","urban_females":"4698"}
{"area":"HIMACHAL_PRADESH","area_code":"2","age":"42","total_persons":"93789","total_males":"47054","total_females":"46735","rural_persons":"83036","rural_males":"41253","rural_females":"41783","urban_persons":"10753","urban_males":"5801","urban_females":"4952"}
{"area":"HIMACHAL_PRADESH","area_code":"2","age":"43","total_persons":"71844","total_males":"36356","total_females":"35488","rural_persons":"63136","rural_males":"31709","rural_females":"31427","urban_persons":"8708","urban_males":"4647","urban_females":"4061"}
{"area":"HIMACHAL_PRADESH","area_code":"2","age":"44","total_persons":"70776","total_males":"35631","total_females":"35145","rural_persons":"62375","rural_males":"31103","rural_females":"31272","urban_persons":"8401","urban_males":"4528","urban_females":"3873"}
{"area":"HIMACHAL_PRADESH","area_code":"2","age":"45","total_persons":"114338","total_males":"54723","total_females":"59615","rural_persons":"102653","rural_males":"48391","rural_females":"54262","urban_persons":"11685","urban_males":"6332","urban_females":"5353"}
{"area":"HIMACHAL_PRADESH","area_code":"2","age":"46","total_persons":"79664","total_males":"40122","total_females":"39542","rural_persons":"70281","rural_males":"35053","rural_females":"35228","urban_persons":"9383","urban_males":"5069","urban_females":"4314"}
{"area":"HIMACHAL_PRADESH","area_code":"2","age":"47","total_persons":"64515","total_males":"33269","total_females":"31246","rural_persons":"56897","rural_males":"29059","rural_females":"27838","urban_persons":"7618","urban_males":"4210","urban_females":"3408"}
{"area":"HIMACHAL_PRADESH","area_code":"2","age":"48","total_persons":"81011","total_males":"40409","total_females":"40602","rural_persons":"72100","rural_males":"35635","rural_females":"36465","urban_persons":"8911","urban_males":"4774","urban_females":"4137"}
{"area":"HIMACHAL_PRADESH","area_code":"2","age":"49","total_persons":"55600","total_males":"29119","total_females":"26481","rural_persons":"48862","rural_males":"25351","rural_females":"23511","urban_persons":"6738","urban_males":"3768","urban_females":"2970"}
{"area":"HIMACHAL_PRADESH","area_code":"2","age":"50","total_persons":"108972","total_males":"49852","total_females":"59120","rural_persons":"99173","rural_males":"44593","rural_females":"54580","urban_persons":"9799","urban_males":"5259","urban_females":"4540"}
{"area":"HIMACHAL_PRADESH","area_code":"2","age":"51","total_persons":"58977","total_males":"30779","total_females":"28198","rural_persons":"52177","rural_males":"26876","rural_females":"25301","urban_persons":"6800","urban_males":"3903","urban_females":"2897"}
{"area":"HIMACHAL_PRADESH","area_code":"2","age":"52","total_persons":"63217","total_males":"32700","total_females":"30517","rural_persons":"56343","rural_males":"28735","rural_females":"27608","urban_persons":"6874","urban_males":"3965","urban_females":"2909"}
{"area":"HIMACHAL_PRADESH","area_code":"2","age":"53","total_persons":"48694","total_males":"25901","total_females":"22793","rural_persons":"42903","rural_males":"22559","rural_females":"20344","urban_persons":"5791","urban_males":"3342","urban_females":"2449"}
{"area":"HIMACHAL_PRADESH","area_code":"2","age":"54","total_persons":"50827","total_males":"26492","total_females":"24335","rural_persons":"44815","rural_males":"23029","rural_females":"21786","urban_persons":"6012","urban_males":"3463","urban_females":"2549"}
{"area":"HIMACHAL_PRADESH","area_code":"2","age":"55","total_persons":"85230","total_males":"39322","total_females":"45908","rural_persons":"77713","rural_males":"35262","rural_females":"42451","urban_persons":"7517","urban_males":"4060","urban_females":"3457"}
{"area":"HIMACHAL_PRADESH","area_code":"2","age":"56","total_persons":"56671","total_males":"29535","total_females":"27136","rural_persons":"50801","rural_males":"26102","rural_females":"24699","urban_persons":"5870","urban_males":"3433","urban_females":"2437"}
{"area":"HIMACHAL_PRADESH","area_code":"2","age":"57","total_persons":"40289","total_males":"21949","total_females":"18340","rural_persons":"35616","rural_males":"19133","rural_females":"16483","urban_persons":"4673","urban_males":"2816","urban_females":"1857"}
{"area":"HIMACHAL_PRADESH","area_code":"2","age":"58","total_persons":"49791","total_males":"25505","total_females":"24286","rural_persons":"44843","rural_males":"22724","rural_females":"22119","urban_persons":"4948","urban_males":"2781","urban_females":"2167"}
{"area":"HIMACHAL_PRADESH","area_code":"2","age":"59","total_persons":"34879","total_males":"18934","total_females":"15945","rural_persons":"31120","rural_males":"16777","rural_females":"14343","urban_persons":"3759","urban_males":"2157","urban_females":"1602"}
{"area":"HIMACHAL_PRADESH","area_code":"2","age":"60","total_persons":"85300","total_males":"36833","total_females":"48467","rural_persons":"79385","rural_males":"33923","rural_females":"45462","urban_persons":"5915","urban_males":"2910","urban_females":"3005"}
{"area":"HIMACHAL_PRADESH","area_code":"2","age":"61","total_persons":"40296","total_males":"20941","total_females":"19355","rural_persons":"36600","rural_males":"18863","rural_females":"17737","urban_persons":"3696","urban_males":"2078","urban_females":"1618"}
{"area":"HIMACHAL_PRADESH","area_code":"2","age":"62","total_persons":"41435","total_males":"21900","total_females":"19535","rural_persons":"37972","rural_males":"20056","rural_females":"17916","urban_persons":"3463","urban_males":"1844","urban_females":"1619"}
{"area":"HIMACHAL_PRADESH","area_code":"2","age":"63","total_persons":"34977","total_males":"19812","total_females":"15165","rural_persons":"31628","rural_males":"17923","rural_females":"13705","urban_persons":"3349","urban_males":"1889","urban_females":"1460"}
{"area":"HIMACHAL_PRADESH","area_code":"2","age":"64","total_persons":"29364","total_males":"15978","total_females":"13386","rural_persons":"26678","rural_males":"14566","rural_females":"12112","urban_persons":"2686","urban_males":"1412","urban_females":"1274"}
{"area":"HIMACHAL_PRADESH","area_code":"2","age":"65","total_persons":"62328","total_males":"27313","total_females":"35015","rural_persons":"58255","rural_males":"25442","rural_females":"32813","urban_persons":"4073","urban_males":"1871","urban_females":"2202"}
{"area":"HIMACHAL_PRADESH","area_code":"2","age":"66","total_persons":"31639","total_males":"16313","total_females":"15326","rural_persons":"29100","rural_males":"14964","rural_females":"14136","urban_persons":"2539","urban_males":"1349","urban_females":"1190"}
{"area":"HIMACHAL_PRADESH","area_code":"2","age":"67","total_persons":"21287","total_males":"12005","total_females":"9282","rural_persons":"19285","rural_males":"10889","rural_females":"8396","urban_persons":"2002","urban_males":"1116","urban_females":"886"}
{"area":"HIMACHAL_PRADESH","area_code":"2","age":"68","total_persons":"25399","total_males":"13304","total_females":"12095","rural_persons":"23150","rural_males":"12089","rural_females":"11061","urban_persons":"2249","urban_males":"1215","urban_females":"1034"}
{"area":"HIMACHAL_PRADESH","area_code":"2","age":"69","total_persons":"17954","total_males":"9452","total_females":"8502","rural_persons":"16306","rural_males":"8566","rural_females":"7740","urban_persons":"1648","urban_males":"886","urban_females":"762"}
{"area":"HIMACHAL_PRADESH","area_code":"2","age":"70","total_persons":"61230","total_males":"25786","total_females":"35444","rural_persons":"57692","rural_males":"24239","rural_females":"33453","urban_persons":"3538","urban_males":"1547","urban_females":"1991"}
{"area":"HIMACHAL_PRADESH","area_code":"2","age":"71","total_persons":"23558","total_males":"11562","total_females":"11996","rural_persons":"21563","rural_males":"10530","rural_females":"11033","urban_persons":"1995","urban_males":"1032","urban_females":"963"}
{"area":"HIMACHAL_PRADESH","area_code":"2","age":"72","total_persons":"19302","total_males":"10199","total_females":"9103","rural_persons":"17704","rural_males":"9344","rural_females":"8360","urban_persons":"1598","urban_males":"855","urban_females":"743"}
{"area":"HIMACHAL_PRADESH","area_code":"2","age":"73","total_persons":"13423","total_males":"7484","total_females":"5939","rural_persons":"12153","rural_males":"6720","rural_females":"5433","urban_persons":"1270","urban_males":"764","urban_females":"506"}
{"area":"HIMACHAL_PRADESH","area_code":"2","age":"74","total_persons":"13074","total_males":"7088","total_females":"5986","rural_persons":"11820","rural_males":"6417","rural_females":"5403","urban_persons":"1254","urban_males":"671","urban_females":"583"}
{"area":"HIMACHAL_PRADESH","area_code":"2","age":"75","total_persons":"33633","total_males":"14636","total_females":"18997","rural_persons":"31516","rural_males":"13705","rural_females":"17811","urban_persons":"2117","urban_males":"931","urban_females":"1186"}
{"area":"HIMACHAL_PRADESH","area_code":"2","age":"76","total_persons":"15135","total_males":"7517","total_females":"7618","rural_persons":"13893","rural_males":"6889","rural_females":"7004","urban_persons":"1242","urban_males":"628","urban_females":"614"}
{"area":"HIMACHAL_PRADESH","area_code":"2","age":"77","total_persons":"8530","total_males":"4766","total_females":"3764","rural_persons":"7683","rural_males":"4285","rural_females":"3398","urban_persons":"847","urban_males":"481","urban_females":"366"}
{"area":"HIMACHAL_PRADESH","area_code":"2","age":"78","total_persons":"10597","total_males":"5476","total_females":"5121","rural_persons":"9723","rural_males":"4992","rural_females":"4731","urban_persons":"874","urban_males":"484","urban_females":"390"}
{"area":"HIMACHAL_PRADESH","area_code":"2","age":"79","total_persons":"7811","total_males":"4045","total_females":"3766","rural_persons":"7143","rural_males":"3690","rural_females":"3453","urban_persons":"668","urban_males":"355","urban_females":"313"}
{"area":"HIMACHAL_PRADESH","area_code":"2","age":"80","total_persons":"31612","total_males":"13028","total_females":"18584","rural_persons":"30010","rural_males":"12367","rural_females":"17643","urban_persons":"1602","urban_males":"661","urban_females":"941"}
{"area":"HIMACHAL_PRADESH","area_code":"2","age":"81","total_persons":"10589","total_males":"4737","total_females":"5852","rural_persons":"9900","rural_males":"4434","rural_females":"5466","urban_persons":"689","urban_males":"303","urban_females":"386"}
{"area":"HIMACHAL_PRADESH","area_code":"2","age":"82","total_persons":"6754","total_males":"3463","total_females":"3291","rural_persons":"6229","rural_males":"3186","rural_females":"3043","urban_persons":"525","urban_males":"277","urban_females":"248"}
{"area":"HIMACHAL_PRADESH","area_code":"2","age":"83","total_persons":"4583","total_males":"2526","total_females":"2057","rural_persons":"4167","rural_males":"2293","rural_females":"1874","urban_persons":"416","urban_males":"233","urban_females":"183"}
{"area":"HIMACHAL_PRADESH","area_code":"2","age":"84","total_persons":"4545","total_males":"2410","total_females":"2135","rural_persons":"4108","rural_males":"2168","rural_females":"1940","urban_persons":"437","urban_males":"242","urban_females":"195"}
{"area":"HIMACHAL_PRADESH","area_code":"2","age":"85","total_persons":"12502","total_males":"5558","total_females":"6944","rural_persons":"11810","rural_males":"5241","rural_females":"6569","urban_persons":"692","urban_males":"317","urban_females":"375"}
{"area":"HIMACHAL_PRADESH","area_code":"2","age":"86","total_persons":"5152","total_males":"2489","total_females":"2663","rural_persons":"4786","rural_males":"2311","rural_females":"2475","urban_persons":"366","urban_males":"178","urban_females":"188"}
{"area":"HIMACHAL_PRADESH","area_code":"2","age":"87","total_persons":"2702","total_males":"1479","total_females":"1223","rural_persons":"2460","rural_males":"1351","rural_females":"1109","urban_persons":"242","urban_males":"128","urban_females":"114"}
{"area":"HIMACHAL_PRADESH","area_code":"2","age":"88","total_persons":"2483","total_males":"1290","total_females":"1193","rural_persons":"2261","rural_males":"1174","rural_females":"1087","urban_persons":"222","urban_males":"116","urban_females":"106"}
{"area":"HIMACHAL_PRADESH","area_code":"2","age":"89","total_persons":"1952","total_males":"1005","total_females":"947","rural_persons":"1806","rural_males":"936","rural_females":"870","urban_persons":"146","urban_males":"69","urban_females":"77"}
{"area":"HIMACHAL_PRADESH","area_code":"2","age":"90","total_persons":"8388","total_males":"3501","total_females":"4887","rural_persons":"8023","rural_males":"3361","rural_females":"4662","urban_persons":"365","urban_males":"140","urban_females":"225"}
{"area":"HIMACHAL_PRADESH","area_code":"2","age":"91","total_persons":"2698","total_males":"1214","total_females":"1484","rural_persons":"2562","rural_males":"1149","rural_females":"1413","urban_persons":"136","urban_males":"65","urban_females":"71"}
{"area":"HIMACHAL_PRADESH","area_code":"2","age":"92","total_persons":"1499","total_males":"724","total_females":"775","rural_persons":"1384","rural_males":"672","rural_females":"712","urban_persons":"115","urban_males":"52","urban_females":"63"}
{"area":"HIMACHAL_PRADESH","area_code":"2","age":"93","total_persons":"1047","total_males":"517","total_females":"530","rural_persons":"967","rural_males":"471","rural_females":"496","urban_persons":"80","urban_males":"46","urban_females":"34"}
{"area":"HIMACHAL_PRADESH","area_code":"2","age":"94","total_persons":"917","total_males":"456","total_females":"461","rural_persons":"840","rural_males":"424","rural_females":"416","urban_persons":"77","urban_males":"32","urban_females":"45"}
{"area":"HIMACHAL_PRADESH","area_code":"2","age":"95","total_persons":"2487","total_males":"1059","total_females":"1428","rural_persons":"2338","rural_males":"1006","rural_females":"1332","urban_persons":"149","urban_males":"53","urban_females":"96"}
{"area":"HIMACHAL_PRADESH","area_code":"2","age":"96","total_persons":"1127","total_males":"503","total_females":"624","rural_persons":"1056","rural_males":"467","rural_females":"589","urban_persons":"71","urban_males":"36","urban_females":"35"}
{"area":"HIMACHAL_PRADESH","area_code":"2","age":"97","total_persons":"630","total_males":"320","total_females":"310","rural_persons":"573","rural_males":"292","rural_females":"281","urban_persons":"57","urban_males":"28","urban_females":"29"}
{"area":"HIMACHAL_PRADESH","area_code":"2","age":"98","total_persons":"886","total_males":"399","total_females":"487","rural_persons":"837","rural_males":"370","rural_females":"467","urban_persons":"49","urban_males":"29","urban_females":"20"}
{"area":"HIMACHAL_PRADESH","area_code":"2","age":"99","total_persons":"665","total_males":"269","total_females":"396","rural_persons":"635","rural_males":"260","rural_females":"375","urban_persons":"30","urban_males":"9","urban_females":"21"}
{"area":"HIMACHAL_PRADESH","area_code":"2","age":"100+","total_persons":"3519","total_males":"1518","total_females":"2001","rural_persons":"3291","rural_males":"1406","rural_females":"1885","urban_persons":"228","urban_males":"112","urban_females":"116"}
{"area":"HIMACHAL_PRADESH","area_code":"2","age":"age_not_stated","total_persons":"10163","total_males":"5353","total_females":"4810","rural_persons":"9386","rural_males":"4899","rural_females":"4487","urban_persons":"777","urban_males":"454","urban_females":"323"}
